<?xml version="1.0" encoding="UTF-8"?>
<ROM>
  <VersionName>dotOS-O-v2.5-mobee01a-OFFICIAL-20180914</VersionName>
  <VersionNumber type="integer">20180914</VersionNumber>
  <DirectUrl>https://sourceforge.net/projects/dotos-2-x/files/mobee01a/dotOS-O-v2.5-mobee01a-OFFICIAL-20180914.zip</DirectUrl>
  <Android>8.1.0</Android>
  <CheckMD5>da68418899456244f93342d4219ee10c</CheckMD5>
  <FileSize type="integer">427410871</FileSize>
  <Changelog>
	<System>dotOS 2.5 Final Release</System>
	<Settings>Bug Fixes</Settings>
	<Misc>Complete changlogs: https://blog.droidontime.com/changes/changelog%202.5.html</Misc>
	<SecurityPatch>September 05th 2018</SecurityPatch>
  </Changelog>
</ROM>
